HibernateKuangjiaRumenjiaochengCYuyanBianchengWangFix1/README.md
HibernateKuangjiaRumenjiaochengCYuyanBianchengWangFix1/__init__.py
HibernateKuangjiaRumenjiaochengCYuyanBianchengWangFix1/__main__.py
HibernateKuangjiaRumenjiaochengCYuyanBianchengWangFix1/file.epub
HibernateKuangjiaRumenjiaochengCYuyanBianchengWangFix1/index.html
HibernateKuangjiaRumenjiaochengCYuyanBianchengWangFix1/css/__init__.py
HibernateKuangjiaRumenjiaochengCYuyanBianchengWangFix1/css/annotations.css
HibernateKuangjiaRumenjiaochengCYuyanBianchengWangFix1/css/main.css
HibernateKuangjiaRumenjiaochengCYuyanBianchengWangFix1/css/normalize.css
HibernateKuangjiaRumenjiaochengCYuyanBianchengWangFix1/css/popup.css
HibernateKuangjiaRumenjiaochengCYuyanBianchengWangFix1/font/__init__.py
HibernateKuangjiaRumenjiaochengCYuyanBianchengWangFix1/font/fontello.eot
HibernateKuangjiaRumenjiaochengCYuyanBianchengWangFix1/font/fontello.svg
HibernateKuangjiaRumenjiaochengCYuyanBianchengWangFix1/font/fontello.ttf
HibernateKuangjiaRumenjiaochengCYuyanBianchengWangFix1/font/fontello.woff
HibernateKuangjiaRumenjiaochengCYuyanBianchengWangFix1/img/__init__.py
HibernateKuangjiaRumenjiaochengCYuyanBianchengWangFix1/img/annotator-glyph-sprite.png
HibernateKuangjiaRumenjiaochengCYuyanBianchengWangFix1/img/annotator-icon-sprite.png
HibernateKuangjiaRumenjiaochengCYuyanBianchengWangFix1/img/apple-touch-icon.png
HibernateKuangjiaRumenjiaochengCYuyanBianchengWangFix1/img/cancelfullscreen.png
HibernateKuangjiaRumenjiaochengCYuyanBianchengWangFix1/img/close.png
HibernateKuangjiaRumenjiaochengCYuyanBianchengWangFix1/img/fullscreen.png
HibernateKuangjiaRumenjiaochengCYuyanBianchengWangFix1/img/loader.gif
HibernateKuangjiaRumenjiaochengCYuyanBianchengWangFix1/img/menu-icon.png
HibernateKuangjiaRumenjiaochengCYuyanBianchengWangFix1/img/save.png
HibernateKuangjiaRumenjiaochengCYuyanBianchengWangFix1/img/saved.png
HibernateKuangjiaRumenjiaochengCYuyanBianchengWangFix1/img/settings-s.png
hibernate_kuangjia_rumenjiaocheng_c_yuyan_biancheng_wang_fix1-2025.3.24.0.dist-info/METADATA
hibernate_kuangjia_rumenjiaocheng_c_yuyan_biancheng_wang_fix1-2025.3.24.0.dist-info/WHEEL
hibernate_kuangjia_rumenjiaocheng_c_yuyan_biancheng_wang_fix1-2025.3.24.0.dist-info/entry_points.txt
hibernate_kuangjia_rumenjiaocheng_c_yuyan_biancheng_wang_fix1-2025.3.24.0.dist-info/top_level.txt
hibernate_kuangjia_rumenjiaocheng_c_yuyan_biancheng_wang_fix1-2025.3.24.0.dist-info/RECORD
